oathnet/__init__.py
oathnet/client.py
oathnet/exceptions.py
oathnet/models.py
oathnet/utils.py
oathnet/services/__init__.py
oathnet/services/exports.py
oathnet/services/file_search.py
oathnet/services/osint.py
oathnet/services/search.py
oathnet/services/stealer_v2.py
oathnet/services/utility.py
oathnet/services/victims.py
oathnet_cli/__init__.py
oathnet_cli/main.py
oathnet_cli/utils.py
oathnet_cli/commands/__init__.py
oathnet_cli/commands/exports.py
oathnet_cli/commands/file_search.py
oathnet_cli/commands/osint.py
oathnet_cli/commands/search.py
oathnet_cli/commands/stealer.py
oathnet_cli/commands/utility.py
oathnet_cli/commands/victims.py
oathnet-1.0.3.dist-info/METADATA
oathnet-1.0.3.dist-info/WHEEL
oathnet-1.0.3.dist-info/entry_points.txt
oathnet-1.0.3.dist-info/RECORD
